DESCRIPTION.rst
MANIFEST.in
README.rst
setup.cfg
setup.py
wuppercodegen/__init__.py
wuppercodegen/cli.py
wuppercodegen/version.py
wuppercodegen.egg-info/PKG-INFO
wuppercodegen.egg-info/SOURCES.txt
wuppercodegen.egg-info/dependency_links.txt
wuppercodegen.egg-info/entry_points.txt
wuppercodegen.egg-info/requires.txt
wuppercodegen.egg-info/top_level.txt