Metadata-Version: 1.1
Name: wuppercodegen
Version: 0.5.2
Summary: The WUPPER Code Generator
Home-page: http://pythonhosted.org/wuppercodegen
Author: Mark Donszelmann, Jose Valenciano, Jorn Schumacher
Author-email: mark.donszelmann@cern.ch
License: APACHE-LICENSE-2.0
Keywords: development
Platform: UNKNOWN
Classifier: Development Status :: 4 - Beta
Classifier: Intended Audience :: Developers
Classifier: Topic :: Software Development :: Build Tools
Classifier: License :: OSI Approved :: Apache Software License
Classifier: Programming Language :: Python :: 2.6
Classifier: Programming Language :: Python :: 2.7
